flask_image_compressor/__init__.py
flask_image_compressor-0.1.0.dist-info/METADATA
flask_image_compressor-0.1.0.dist-info/WHEEL
flask_image_compressor-0.1.0.dist-info/top_level.txt
flask_image_compressor-0.1.0.dist-info/RECORD
