Metadata-Version: 2.4
Name: flask-image-compressor
Version: 0.1.0
Summary: A Flask extension for automatic image compression and optimization
Home-page: https://github.com/gnubyte/flask-image-compressor
Author: gnubyte
Author-email: gnubyte@users.noreply.github.com
Classifier: Programming Language :: Python :: 3
Classifier: License :: OSI Approved :: MIT License
Classifier: Operating System :: OS Independent
Requires-Python: >=3.6
Requires-Dist: flask
Requires-Dist: werkzeug
Requires-Dist: pillow
Dynamic: author
Dynamic: author-email
Dynamic: classifier
Dynamic: description
Dynamic: description-content-type
Dynamic: home-page
Dynamic: requires-dist
Dynamic: requires-python
Dynamic: summary
